<annotation>
	<folder>Bike_all</folder>
	<filename>117.jpg</filename>
	<path>/Users/hushengzhe/Desktop/Bike_all/117.jpg</path>
	<source>
		<database>Unknown</database>
	</source>
	<size>
		<width>1024</width>
		<height>568</height>
		<depth>3</depth>
	</size>
	<segmented>0</segmented>
	<object>
		<name>Bike_toward</name>
		<pose>Unspecified</pose>
		<truncated>1</truncated>
		<difficult>0</difficult>
		<bndbox>
			<xmin>220</xmin>
			<ymin>314</ymin>
			<xmax>741</xmax>
			<ymax>568</ymax>
		</bndbox>
	</object>
</annotation>
