<annotation>
	<folder>Bike_all</folder>
	<filename>238.jpg</filename>
	<path>/Users/hushengzhe/Desktop/Bike_all/238.jpg</path>
	<source>
		<database>Unknown</database>
	</source>
	<size>
		<width>672</width>
		<height>1024</height>
		<depth>3</depth>
	</size>
	<segmented>0</segmented>
	<object>
		<name>Bike_away</name>
		<pose>Unspecified</pose>
		<truncated>0</truncated>
		<difficult>0</difficult>
		<bndbox>
			<xmin>268</xmin>
			<ymin>530</ymin>
			<xmax>510</xmax>
			<ymax>806</ymax>
		</bndbox>
	</object>
</annotation>
