<annotation>
	<folder>stop</folder>
	<filename>241bb0b26cbd4680.jpg</filename>
	<path>F:\MSDA\298B\data_openimage\stop\241bb0b26cbd4680.jpg</path>
	<source>
		<database>Unknown</database>
	</source>
	<size>
		<width>1024</width>
		<height>768</height>
		<depth>3</depth>
	</size>
	<segmented>0</segmented>
	<object>
		<name>stop_sign</name>
		<pose>Unspecified</pose>
		<truncated>0</truncated>
		<difficult>0</difficult>
		<bndbox>
			<xmin>162</xmin>
			<ymin>173</ymin>
			<xmax>274</xmax>
			<ymax>295</ymax>
		</bndbox>
	</object>
</annotation>
