<annotation>
	<folder>vehicle_images</folder>
	<filename>3422.jpg</filename>
	<path>D:\Data298\Images\vehicle_images\3422.jpg</path>
	<source>
		<database>Unknown</database>
	</source>
	<size>
		<width>1920</width>
		<height>1080</height>
		<depth>3</depth>
	</size>
	<segmented>0</segmented>
	<object>
		<name>vehicle_toward</name>
		<pose>Unspecified</pose>
		<truncated>0</truncated>
		<difficult>0</difficult>
		<bndbox>
			<xmin>1142</xmin>
			<ymin>567</ymin>
			<xmax>1356</xmax>
			<ymax>674</ymax>
		</bndbox>
	</object>
	<object>
		<name>vehicle_toward</name>
		<pose>Unspecified</pose>
		<truncated>0</truncated>
		<difficult>0</difficult>
		<bndbox>
			<xmin>931</xmin>
			<ymin>560</ymin>
			<xmax>989</xmax>
			<ymax>609</ymax>
		</bndbox>
	</object>
</annotation>
