<annotation>
	<folder>Bike_all</folder>
	<filename>963.jpg</filename>
	<path>/Users/hushengzhe/Desktop/Bike_all/963.jpg</path>
	<source>
		<database>Unknown</database>
	</source>
	<size>
		<width>768</width>
		<height>1024</height>
		<depth>3</depth>
	</size>
	<segmented>0</segmented>
	<object>
		<name>Bike_toward</name>
		<pose>Unspecified</pose>
		<truncated>0</truncated>
		<difficult>0</difficult>
		<bndbox>
			<xmin>88</xmin>
			<ymin>536</ymin>
			<xmax>697</xmax>
			<ymax>1002</ymax>
		</bndbox>
	</object>
</annotation>
