<annotation>
	<folder>traffic light</folder>
	<filename>a6b1369a85dd07bc.jpg</filename>
	<path>F:\MSDA\298B\data_openimage\traffic light\a6b1369a85dd07bc.jpg</path>
	<source>
		<database>Unknown</database>
	</source>
	<size>
		<width>1024</width>
		<height>661</height>
		<depth>3</depth>
	</size>
	<segmented>0</segmented>
	<object>
		<name>red_light</name>
		<pose>Unspecified</pose>
		<truncated>0</truncated>
		<difficult>0</difficult>
		<bndbox>
			<xmin>246</xmin>
			<ymin>218</ymin>
			<xmax>271</xmax>
			<ymax>280</ymax>
		</bndbox>
	</object>
	<object>
		<name>red_light</name>
		<pose>Unspecified</pose>
		<truncated>0</truncated>
		<difficult>0</difficult>
		<bndbox>
			<xmin>425</xmin>
			<ymin>114</ymin>
			<xmax>456</xmax>
			<ymax>191</ymax>
		</bndbox>
	</object>
</annotation>
