<annotation>
	<folder>traffic_lights</folder>
	<filename>IMG_1485.JPG</filename>
	<path>F:\MSDA\298B\test_data\traffic_lights\IMG_1485.JPG</path>
	<source>
		<database>Unknown</database>
	</source>
	<size>
		<width>3024</width>
		<height>4032</height>
		<depth>3</depth>
	</size>
	<segmented>0</segmented>
	<object>
		<name>red_light</name>
		<pose>Unspecified</pose>
		<truncated>0</truncated>
		<difficult>0</difficult>
		<bndbox>
			<xmin>1355</xmin>
			<ymin>1177</ymin>
			<xmax>1441</xmax>
			<ymax>1377</ymax>
		</bndbox>
	</object>
	<object>
		<name>red_light</name>
		<pose>Unspecified</pose>
		<truncated>0</truncated>
		<difficult>0</difficult>
		<bndbox>
			<xmin>2468</xmin>
			<ymin>1709</ymin>
			<xmax>2546</xmax>
			<ymax>1909</ymax>
		</bndbox>
	</object>
</annotation>
