<annotation>
	<folder>tree</folder>
	<filename>jimmy-tompkins-YKxMfIKoxvE-unsplash.jpg</filename>
	<path>F:\capstone\new image\tree\jimmy-tompkins-YKxMfIKoxvE-unsplash.jpg</path>
	<source>
		<database>Unknown</database>
	</source>
	<size>
		<width>6000</width>
		<height>4000</height>
		<depth>3</depth>
	</size>
	<segmented>0</segmented>
	<object>
		<name>tree</name>
		<pose>Unspecified</pose>
		<truncated>1</truncated>
		<difficult>0</difficult>
		<bndbox>
			<xmin>1</xmin>
			<ymin>1</ymin>
			<xmax>1825</xmax>
			<ymax>2759</ymax>
		</bndbox>
	</object>
	<object>
		<name>tree</name>
		<pose>Unspecified</pose>
		<truncated>1</truncated>
		<difficult>0</difficult>
		<bndbox>
			<xmin>4056</xmin>
			<ymin>1</ymin>
			<xmax>6000</xmax>
			<ymax>2797</ymax>
		</bndbox>
	</object>
	<object>
		<name>tree</name>
		<pose>Unspecified</pose>
		<truncated>1</truncated>
		<difficult>0</difficult>
		<bndbox>
			<xmin>834</xmin>
			<ymin>1</ymin>
			<xmax>2312</xmax>
			<ymax>2425</ymax>
		</bndbox>
	</object>
</annotation>
