<annotation>
	<folder>pedestrian</folder>
	<filename>schloss-rain-00000921.png</filename>
	<path>C:\Users\Owner\Desktop\data_combine\pedestrian\schloss-rain-00000921.png</path>
	<source>
		<database>Unknown</database>
	</source>
	<size>
		<width>720</width>
		<height>576</height>
		<depth>3</depth>
	</size>
	<segmented>0</segmented>
	<object>
		<name>pedestrian_back</name>
		<pose>Unspecified</pose>
		<truncated>0</truncated>
		<difficult>0</difficult>
		<bndbox>
			<xmin>421</xmin>
			<ymin>174</ymin>
			<xmax>477</xmax>
			<ymax>358</ymax>
		</bndbox>
	</object>
	<object>
		<name>pedestrian_front</name>
		<pose>Unspecified</pose>
		<truncated>0</truncated>
		<difficult>0</difficult>
		<bndbox>
			<xmin>238</xmin>
			<ymin>192</ymin>
			<xmax>284</xmax>
			<ymax>266</ymax>
		</bndbox>
	</object>
</annotation>
