<annotation>
	<folder>dianxiangan</folder>
	<filename>shaylin-wallace-486mV-L4G1E-unsplash.jpg</filename>
	<path>F:\capstone\dianxiangan\shaylin-wallace-486mV-L4G1E-unsplash.jpg</path>
	<source>
		<database>Unknown</database>
	</source>
	<size>
		<width>600</width>
		<height>600</height>
		<depth>3</depth>
	</size>
	<segmented>0</segmented>
	<object>
		<name>utility_pole</name>
		<pose>Unspecified</pose>
		<truncated>0</truncated>
		<difficult>0</difficult>
		<bndbox>
			<xmin>255</xmin>
			<ymin>85</ymin>
			<xmax>321</xmax>
			<ymax>205</ymax>
		</bndbox>
	</object>
	<object>
		<name>utility_pole</name>
		<pose>Unspecified</pose>
		<truncated>0</truncated>
		<difficult>0</difficult>
		<bndbox>
			<xmin>481</xmin>
			<ymin>2</ymin>
			<xmax>547</xmax>
			<ymax>152</ymax>
		</bndbox>
	</object>
	<object>
		<name>utility_pole</name>
		<pose>Unspecified</pose>
		<truncated>0</truncated>
		<difficult>0</difficult>
		<bndbox>
			<xmin>198</xmin>
			<ymin>319</ymin>
			<xmax>264</xmax>
			<ymax>385</ymax>
		</bndbox>
	</object>
</annotation>
