<annotation>
	<folder>utility_pole</folder>
	<filename>WX20200414-190833.png</filename>
	<path>F:\capstone\new images\utility_pole\WX20200414-190833.png</path>
	<source>
		<database>Unknown</database>
	</source>
	<size>
		<width>800</width>
		<height>600</height>
		<depth>3</depth>
	</size>
	<segmented>0</segmented>
	<object>
		<name>utility_pole</name>
		<pose>Unspecified</pose>
		<truncated>0</truncated>
		<difficult>0</difficult>
		<bndbox>
			<xmin>388</xmin>
			<ymin>119</ymin>
			<xmax>433</xmax>
			<ymax>184</ymax>
		</bndbox>
	</object>
	<object>
		<name>tree</name>
		<pose>Unspecified</pose>
		<truncated>0</truncated>
		<difficult>0</difficult>
		<bndbox>
			<xmin>256</xmin>
			<ymin>211</ymin>
			<xmax>527</xmax>
			<ymax>472</ymax>
		</bndbox>
	</object>
</annotation>
