<annotation>
	<folder>tree extra2</folder>
	<filename>WX20200507-221920.png</filename>
	<path>F:\capstone\new images\tree extra2\WX20200507-221920.png</path>
	<source>
		<database>Unknown</database>
	</source>
	<size>
		<width>767</width>
		<height>593</height>
		<depth>3</depth>
	</size>
	<segmented>0</segmented>
	<object>
		<name>tree</name>
		<pose>Unspecified</pose>
		<truncated>0</truncated>
		<difficult>0</difficult>
		<bndbox>
			<xmin>228</xmin>
			<ymin>57</ymin>
			<xmax>617</xmax>
			<ymax>508</ymax>
		</bndbox>
	</object>
</annotation>
